{
  "id": "volvo-ex30-single-motor",
  "slug": "volvo-ex30-single-motor",
  "marca": "Volvo",
  "modelo": "EX30",
  "variante": "Single Motor",
  "nombre_completo": "Volvo EX30 Single Motor",
  "segmento": "SUV",
  "imagen": "/comparador/volvo-ex30-single-motor.webp",
  "specs": {
    "model_year": {
      "valor": null,
      "fuente_tipo": "pendiente",
      "verificado": false
    },
    "carroceria": {
      "valor": null,
      "fuente_tipo": "pendiente",
      "verificado": false
    },
    "estado_comercial": {
      "valor": null,
      "fuente_tipo": "pendiente",
      "verificado": false
    },
    "pais_fabricacion": {
      "valor": null,
      "fuente_tipo": "pendiente",
      "verificado": false
    },
    "plataforma": {
      "valor": null,
      "fuente_tipo": "pendiente",
      "verificado": false
    },
    "fecha_lanzamiento_es": {
      "valor": null,
      "fuente_tipo": "pendiente",
      "verificado": false
    },
    "bateria_neta_kwh": {
      "valor": 49,
      "fuente_tipo": "pendiente",
      "verificado": false,
      "unidad": "kWh"
    },
    "bateria_bruta_kwh": {
      "valor": 51,
      "fuente_tipo": "pendiente",
      "verificado": false,
      "unidad": "kWh"
    },
    "quimica": {
      "valor": "LFP",
      "fuente_tipo": "pendiente",
      "verificado": false
    },
    "fabricante_celda": {
      "valor": null,
      "fuente_tipo": "pendiente",
      "verificado": false
    },
    "formato_celda": {
      "valor": null,
      "fuente_tipo": "pendiente",
      "verificado": false
    },
    "voltaje": {
      "valor": 400,
      "fuente_tipo": "pendiente",
      "verificado": false,
      "unidad": "V"
    },
    "refrigeracion_bateria": {
      "valor": null,
      "fuente_tipo": "pendiente",
      "verificado": false
    },
    "carga_dc_max_kw": {
      "valor": 153,
      "fuente_tipo": "pendiente",
      "verificado": false,
      "unidad": "kW"
    },
    "carga_dc_media_10_80_kw": {
      "valor": null,
      "fuente_tipo": "pendiente",
      "verificado": false,
      "unidad": "kW"
    },
    "t_10_80_min": {
      "valor": 26,
      "fuente_tipo": "pendiente",
      "verificado": false,
      "unidad": "min"
    },
    "t_para_300km_min": {
      "valor": null,
      "fuente_tipo": "pendiente",
      "verificado": false,
      "unidad": "min"
    },
    "carga_ac_max_kw": {
      "valor": 11,
      "fuente_tipo": "pendiente",
      "verificado": false,
      "unidad": "kW"
    },
    "t_carga_completa_ac_h": {
      "valor": null,
      "fuente_tipo": "pendiente",
      "verificado": false,
      "unidad": "h"
    },
    "conector_dc": {
      "valor": "CCS2",
      "fuente_tipo": "pendiente",
      "verificado": false
    },
    "preconditioning_bateria": {
      "valor": null,
      "fuente_tipo": "pendiente",
      "verificado": false
    },
    "plug_and_charge": {
      "valor": null,
      "fuente_tipo": "pendiente",
      "verificado": false
    },
    "v2l_w": {
      "valor": null,
      "fuente_tipo": "pendiente",
      "verificado": false,
      "unidad": "W"
    },
    "v2h": {
      "valor": null,
      "fuente_tipo": "pendiente",
      "verificado": false
    },
    "v2g": {
      "valor": null,
      "fuente_tipo": "pendiente",
      "verificado": false
    },
    "bomba_calor": {
      "valor": "Sí",
      "fuente_tipo": "pendiente",
      "verificado": false
    },
    "autonomia_wltp_km": {
      "valor": 344,
      "fuente_tipo": "pendiente",
      "verificado": false,
      "unidad": "km"
    },
    "autonomia_wltp_urbana_km": {
      "valor": null,
      "fuente_tipo": "pendiente",
      "verificado": false,
      "unidad": "km"
    },
    "consumo_wltp_kwh100km": {
      "valor": 17.5,
      "fuente_tipo": "pendiente",
      "verificado": false,
      "unidad": "kWh/100km"
    },
    "consumo_wltp_ciudad_kwh100km": {
      "valor": null,
      "fuente_tipo": "pendiente",
      "verificado": false,
      "unidad": "kWh/100km"
    },
    "autonomia_real_estimada_km": {
      "valor": null,
      "fuente_tipo": "pendiente",
      "verificado": false,
      "unidad": "km"
    },
    "consumo_real_estimado_kwh100km": {
      "valor": null,
      "fuente_tipo": "pendiente",
      "verificado": false,
      "unidad": "kWh/100km"
    },
    "potencia_kw": {
      "valor": 200,
      "fuente_tipo": "pendiente",
      "verificado": false,
      "unidad": "kW"
    },
    "potencia_cv": {
      "valor": 272,
      "fuente_tipo": "pendiente",
      "verificado": false,
      "unidad": "CV"
    },
    "par_nm": {
      "valor": 343,
      "fuente_tipo": "pendiente",
      "verificado": false,
      "unidad": "Nm"
    },
    "traccion": {
      "valor": "RWD",
      "fuente_tipo": "pendiente",
      "verificado": false
    },
    "n_motores": {
      "valor": 1,
      "fuente_tipo": "pendiente",
      "verificado": false
    },
    "aceleracion_0_100_s": {
      "valor": 5.3,
      "fuente_tipo": "pendiente",
      "verificado": false,
      "unidad": "s"
    },
    "aceleracion_80_120_s": {
      "valor": null,
      "fuente_tipo": "pendiente",
      "verificado": false,
      "unidad": "s"
    },
    "velocidad_max_kmh": {
      "valor": 180,
      "fuente_tipo": "pendiente",
      "verificado": false,
      "unidad": "km/h"
    },
    "largo_mm": {
      "valor": 4233,
      "fuente_tipo": "pendiente",
      "verificado": false,
      "unidad": "mm"
    },
    "ancho_mm": {
      "valor": 1837,
      "fuente_tipo": "pendiente",
      "verificado": false,
      "unidad": "mm"
    },
    "alto_mm": {
      "valor": 1549,
      "fuente_tipo": "pendiente",
      "verificado": false,
      "unidad": "mm"
    },
    "batalla_mm": {
      "valor": 2650,
      "fuente_tipo": "pendiente",
      "verificado": false,
      "unidad": "mm"
    },
    "voladizo_delantero_mm": {
      "valor": null,
      "fuente_tipo": "pendiente",
      "verificado": false,
      "unidad": "mm"
    },
    "voladizo_trasero_mm": {
      "valor": null,
      "fuente_tipo": "pendiente",
      "verificado": false,
      "unidad": "mm"
    },
    "via_delantera_mm": {
      "valor": null,
      "fuente_tipo": "pendiente",
      "verificado": false,
      "unidad": "mm"
    },
    "via_trasera_mm": {
      "valor": null,
      "fuente_tipo": "pendiente",
      "verificado": false,
      "unidad": "mm"
    },
    "diametro_giro_m": {
      "valor": null,
      "fuente_tipo": "pendiente",
      "verificado": false,
      "unidad": "m"
    },
    "cx": {
      "valor": 0.29,
      "fuente_tipo": "pendiente",
      "verificado": false
    },
    "peso_kg": {
      "valor": 1790,
      "fuente_tipo": "pendiente",
      "verificado": false,
      "unidad": "kg"
    },
    "mma_kg": {
      "valor": null,
      "fuente_tipo": "pendiente",
      "verificado": false,
      "unidad": "kg"
    },
    "plazas": {
      "valor": null,
      "fuente_tipo": "pendiente",
      "verificado": false
    },
    "maletero_l": {
      "valor": 318,
      "fuente_tipo": "pendiente",
      "verificado": false,
      "unidad": "L"
    },
    "maletero_abatido_l": {
      "valor": null,
      "fuente_tipo": "pendiente",
      "verificado": false,
      "unidad": "L"
    },
    "frunk_l": {
      "valor": 7,
      "fuente_tipo": "pendiente",
      "verificado": false,
      "unidad": "L"
    },
    "carga_util_kg": {
      "valor": null,
      "fuente_tipo": "pendiente",
      "verificado": false,
      "unidad": "kg"
    },
    "capacidad_remolque_kg": {
      "valor": null,
      "fuente_tipo": "pendiente",
      "verificado": false,
      "unidad": "kg"
    },
    "enganche_remolque_opcional": {
      "valor": null,
      "fuente_tipo": "pendiente",
      "verificado": false
    },
    "euroncap_estrellas": {
      "valor": null,
      "fuente_tipo": "pendiente",
      "verificado": false
    },
    "euroncap_ano_test": {
      "valor": null,
      "fuente_tipo": "pendiente",
      "verificado": false
    },
    "euroncap_adult_occupant_pct": {
      "valor": null,
      "fuente_tipo": "pendiente",
      "verificado": false,
      "unidad": "%"
    },
    "euroncap_child_occupant_pct": {
      "valor": null,
      "fuente_tipo": "pendiente",
      "verificado": false,
      "unidad": "%"
    },
    "euroncap_vulnerable_users_pct": {
      "valor": null,
      "fuente_tipo": "pendiente",
      "verificado": false,
      "unidad": "%"
    },
    "euroncap_safety_assist_pct": {
      "valor": null,
      "fuente_tipo": "pendiente",
      "verificado": false,
      "unidad": "%"
    },
    "adas_nivel": {
      "valor": null,
      "fuente_tipo": "pendiente",
      "verificado": false
    },
    "adas_sistemas": {
      "valor": null,
      "fuente_tipo": "pendiente",
      "verificado": false
    },
    "indice_fiabilidad_enchufa2": {
      "valor": null,
      "fuente_tipo": "pendiente",
      "verificado": false
    },
    "fiabilidad_fuentes": {
      "valor": null,
      "fuente_tipo": "pendiente",
      "verificado": false
    },
    "fiabilidad_anos_datos": {
      "valor": null,
      "fuente_tipo": "pendiente",
      "verificado": false
    },
    "fiabilidad_nota_marca": {
      "valor": null,
      "fuente_tipo": "pendiente",
      "verificado": false
    },
    "pvp": {
      "valor": 36095,
      "fuente_tipo": "pendiente",
      "verificado": false,
      "unidad": "€"
    },
    "pvp_fecha": {
      "valor": "2026-03",
      "fuente_tipo": "pendiente",
      "verificado": false
    },
    "pvp_con_plan_auto_eur": {
      "valor": null,
      "fuente_tipo": "pendiente",
      "verificado": false,
      "unidad": "€"
    },
    "plan_auto_elegible": {
      "valor": "Parcial",
      "fuente_tipo": "pendiente",
      "verificado": false
    },
    "moves_aplicable": {
      "valor": null,
      "fuente_tipo": "pendiente",
      "verificado": false
    },
    "garantia_vehiculo_anos": {
      "valor": null,
      "fuente_tipo": "pendiente",
      "verificado": false,
      "unidad": "años"
    },
    "garantia_vehiculo_km": {
      "valor": null,
      "fuente_tipo": "pendiente",
      "verificado": false,
      "unidad": "km"
    },
    "garantia_bateria_anos": {
      "valor": null,
      "fuente_tipo": "pendiente",
      "verificado": false,
      "unidad": "años"
    },
    "garantia_bateria_km": {
      "valor": null,
      "fuente_tipo": "pendiente",
      "verificado": false,
      "unidad": "km"
    },
    "garantia_bateria": {
      "valor": "8 años / 160.000 km",
      "fuente_tipo": "pendiente",
      "verificado": false
    },
    "soh_minimo_garantizado_pct": {
      "valor": null,
      "fuente_tipo": "pendiente",
      "verificado": false,
      "unidad": "%"
    },
    "mantenimiento_intervalo_anos": {
      "valor": null,
      "fuente_tipo": "pendiente",
      "verificado": false,
      "unidad": "años"
    },
    "mantenimiento_intervalo_km": {
      "valor": null,
      "fuente_tipo": "pendiente",
      "verificado": false,
      "unidad": "km"
    },
    "pantalla_central_pulgadas": {
      "valor": null,
      "fuente_tipo": "pendiente",
      "verificado": false,
      "unidad": "\""
    },
    "ota_updates": {
      "valor": null,
      "fuente_tipo": "pendiente",
      "verificado": false
    },
    "carplay": {
      "valor": null,
      "fuente_tipo": "pendiente",
      "verificado": false
    },
    "android_auto": {
      "valor": null,
      "fuente_tipo": "pendiente",
      "verificado": false
    },
    "camara_360": {
      "valor": null,
      "fuente_tipo": "pendiente",
      "verificado": false
    },
    "head_up_display": {
      "valor": null,
      "fuente_tipo": "pendiente",
      "verificado": false
    },
    "climatizador": {
      "valor": null,
      "fuente_tipo": "pendiente",
      "verificado": false
    },
    "asientos_calefactados": {
      "valor": null,
      "fuente_tipo": "pendiente",
      "verificado": false
    },
    "asientos_ventilados": {
      "valor": null,
      "fuente_tipo": "pendiente",
      "verificado": false
    },
    "techo_panoramico": {
      "valor": null,
      "fuente_tipo": "pendiente",
      "verificado": false
    }
  },
  "meta": {
    "fecha_actualizacion": null,
    "estado": "pendiente",
    "notas_my": null
  }
}
